enhanced_str/__init__.py
enhanced_str/mod.py
enhanced_str/utils.py
enhanced_str-0.0.7.dist-info/LICENSE
enhanced_str-0.0.7.dist-info/METADATA
enhanced_str-0.0.7.dist-info/WHEEL
enhanced_str-0.0.7.dist-info/top_level.txt
enhanced_str-0.0.7.dist-info/RECORD
