Metadata-Version: 2.1
Name: enhanced-str
Version: 0.0.7
Summary: A Python library for prettier, fully customizable console outputs.
Author: saschawhy
Keywords: python,console,output,pretty,print
Classifier: Development Status :: 1 - Planning
Classifier: Intended Audience :: Developers
Classifier: Programming Language :: Python :: 3
Classifier: Operating System :: Unix
Classifier: Operating System :: MacOS :: MacOS X
Classifier: Operating System :: Microsoft :: Windows
License-File: LICENSE
